GTC_Pygame_Runtime_Support/__init__.py
GTC_Pygame_Runtime_Support/adjust_box.py
GTC_Pygame_Runtime_Support/basic_class.py
GTC_Pygame_Runtime_Support/button.py
GTC_Pygame_Runtime_Support/checker.py
GTC_Pygame_Runtime_Support/drag_area.py
GTC_Pygame_Runtime_Support/drag_down.py
GTC_Pygame_Runtime_Support/drop_down.py
GTC_Pygame_Runtime_Support/error.py
GTC_Pygame_Runtime_Support/file_drag_area.py
GTC_Pygame_Runtime_Support/input_box.py
GTC_Pygame_Runtime_Support/input_box.pyi
GTC_Pygame_Runtime_Support/page.py
GTC_Pygame_Runtime_Support/popup.py
GTC_Pygame_Runtime_Support/progress_bar.py
GTC_Pygame_Runtime_Support/return_type.py
GTC_Pygame_Runtime_Support/slider.py
GTC_Pygame_Runtime_Support/supported_types.py
GTC_Pygame_Runtime_Support/surface.py
GTC_Pygame_Runtime_Support/test.py
GTC_Pygame_Runtime_Support/typography.py
GTC_Pygame_Runtime_Support/combined_widget/__init__.py
GTC_Pygame_Runtime_Support/combined_widget/page_y_slider.py
gtc_pygame_runtime_support-0.0.23.dist-info/METADATA
gtc_pygame_runtime_support-0.0.23.dist-info/WHEEL
gtc_pygame_runtime_support-0.0.23.dist-info/licenses/LICENSE
gtc_pygame_runtime_support-0.0.23.dist-info/RECORD
