Metadata-Version: 2.4
Name: GTC_Pygame_Runtime_Support
Version: 0.0.23
Summary: Integrated Pygame application development support.
Project-URL: Repository, https://github.com/GTC-Software-Studio/GTC-Pygame-Runtime-Support/
Project-URL: Documentation, https://www.yuque.com/tdkjzx/gtc_prs
Author-email: GTC Byzantine <w1127inline@outlook.com>
License-Expression: GPL-3.0-only
License-File: LICENSE
Keywords: development,pygame,software
Classifier: Development Status :: 2 - Pre-Alpha
Classifier: Intended Audience :: Developers
Classifier: License :: OSI Approved :: GNU General Public License v3 (GPLv3)
Classifier: Programming Language :: Python :: 3
Classifier: Programming Language :: Python :: 3.7
Classifier: Programming Language :: Python :: 3.8
Classifier: Programming Language :: Python :: 3.9
Classifier: Programming Language :: Python :: 3.10
Classifier: Programming Language :: Python :: 3.11
Classifier: Programming Language :: Python :: 3.12
Requires-Dist: pygame
